azure/confidentialledger/certificate/__init__.py
azure/confidentialledger/certificate/_client.py
azure/confidentialledger/certificate/_configuration.py
azure/confidentialledger/certificate/_patch.py
azure/confidentialledger/certificate/_version.py
azure/confidentialledger/certificate/py.typed
azure/confidentialledger/certificate/_operations/__init__.py
azure/confidentialledger/certificate/_operations/_operations.py
azure/confidentialledger/certificate/_operations/_patch.py
azure/confidentialledger/certificate/_utils/__init__.py
azure/confidentialledger/certificate/_utils/model_base.py
azure/confidentialledger/certificate/_utils/serialization.py
azure/confidentialledger/certificate/_utils/utils.py
azure/confidentialledger/certificate/aio/__init__.py
azure/confidentialledger/certificate/aio/_client.py
azure/confidentialledger/certificate/aio/_configuration.py
azure/confidentialledger/certificate/aio/_patch.py
azure/confidentialledger/certificate/aio/_operations/__init__.py
azure/confidentialledger/certificate/aio/_operations/_operations.py
azure/confidentialledger/certificate/aio/_operations/_patch.py
azure/confidentialledger/certificate/models/__init__.py
azure/confidentialledger/certificate/models/_models.py
azure/confidentialledger/certificate/models/_patch.py
azure_confidentialledger_certificate-1.0.0b1.dist-info/licenses/LICENSE
azure_confidentialledger_certificate-1.0.0b1.dist-info/METADATA
azure_confidentialledger_certificate-1.0.0b1.dist-info/WHEEL
azure_confidentialledger_certificate-1.0.0b1.dist-info/top_level.txt
azure_confidentialledger_certificate-1.0.0b1.dist-info/RECORD
